{
	"name": "DelimitedText1",
	"properties": {
		"linkedServiceName": {
			"referenceName": "NotoficationStorage",
			"type": "LinkedServiceReference"
		},
		"annotations": [],
		"type": "DelimitedText",
		"typeProperties": {
			"location": {
				"type": "AzureBlobStorageLocation",
				"fileName": "Employees.csv",
				"container": "employee"
			},
			"columnDelimiter": ";",
			"escapeChar": "\\",
			"firstRowAsHeader": true,
			"quoteChar": "\""
		},
		"schema": [
			{
				"name": "ID",
				"type": "String"
			},
			{
				"name": "Email",
				"type": "String"
			},
			{
				"name": "Phone",
				"type": "String"
			}
		]
	}
}